access_nri_intake/__init__.py
access_nri_intake/_version.py
access_nri_intake/cli.py
access_nri_intake/utils.py
access_nri_intake/catalog/__init__.py
access_nri_intake/catalog/manager.py
access_nri_intake/catalog/translators.py
access_nri_intake/catalog/utils.py
access_nri_intake/data/__init__.py
access_nri_intake/data/catalog.yaml
access_nri_intake/data/metadata_schema_experiment.json
access_nri_intake/data/metadata_schema_file.json
access_nri_intake/data/utils.py
access_nri_intake/experiment/__init__.py
access_nri_intake/experiment/colours.py
access_nri_intake/experiment/main.py
access_nri_intake/experiment/utils.py
access_nri_intake/ipython_magic/__init__.py
access_nri_intake/ipython_magic/ast.py
access_nri_intake/source/__init__.py
access_nri_intake/source/builders.py
access_nri_intake/source/utils.py
access_nri_intake-1.5.0.dist-info/licenses/LICENSE
access_nri_intake-1.5.0.dist-info/METADATA
access_nri_intake-1.5.0.dist-info/WHEEL
access_nri_intake-1.5.0.dist-info/entry_points.txt
access_nri_intake-1.5.0.dist-info/top_level.txt
access_nri_intake-1.5.0.dist-info/RECORD
