Metadata-Version: 2.4
Name: access_nri_intake
Version: 1.5.0
Summary: Intake catalog managed by ACCESS-NRI and associated tools
Author: ACCESS-NRI
License: Apache-2.0
Classifier: Development Status :: 4 - Beta
Classifier: Programming Language :: Python :: 3
Classifier: License :: OSI Approved :: Apache Software License
Classifier: Operating System :: OS Independent
Requires-Python: >=3.10
License-File: LICENSE
Requires-Dist: cftime
Requires-Dist: ecgtools-access
Requires-Dist: frozendict
Requires-Dist: intake>=2.0.0
Requires-Dist: intake-dataframe-catalog>=0.3.1
Requires-Dist: intake-esm-access
Requires-Dist: jsonschema
Requires-Dist: libcst
Requires-Dist: pydantic
Requires-Dist: polars>=1.24.0
Requires-Dist: pooch
Requires-Dist: xarray
Requires-Dist: colorama
Requires-Dist: yamanifest>=0.3.12
Requires-Dist: access-py-telemetry>=0.1.6
Provides-Extra: test
Requires-Dist: pytest; extra == "test"
Requires-Dist: tox; extra == "test"
Provides-Extra: e2e
Requires-Dist: pytest; extra == "e2e"
Requires-Dist: pytest-ordering; extra == "e2e"
Dynamic: license-file
